<annotation>
  <folder>images</folder>
  <filename>10063.jpg</filename>
  <path>C:\Users\Acer\object_detection_demo\object_detection_demo\data\images\10063.jpg</path>
  <source>
    <database>Unknown</database>
  </source>
  <size>
    <width>800</width>
    <height>600</height>
    <depth>3</depth>
  </size>
  <segmented>0</segmented>
  <object>
    <name>TsisyArotava</name>
    <pose>Unspecified</pose>
    <truncated>0</truncated>
    <difficult>0</difficult>
    <bndbox>
      <xmin>265</xmin>
      <ymin>58</ymin>
      <xmax>325</xmax>
      <ymax>176</ymax>
    </bndbox>
  </object>
  <object>
    <name>TsisyArotava</name>
    <pose>Unspecified</pose>
    <truncated>0</truncated>
    <difficult>0</difficult>
    <bndbox>
      <xmin>437</xmin>
      <ymin>142</ymin>
      <xmax>508</xmax>
      <ymax>243</ymax>
    </bndbox>
  </object>
  <object>
    <name>TsisyArotava</name>
    <pose>Unspecified</pose>
    <truncated>0</truncated>
    <difficult>0</difficult>
    <bndbox>
      <xmin>569</xmin>
      <ymin>182</ymin>
      <xmax>637</xmax>
      <ymax>285</ymax>
    </bndbox>
  </object>
</annotation>
