<annotation>
  <folder>rect</folder>
  <filename>5000170.jpg</filename>
  <path>D:\safidy priver\AI\ML kit\model archive cocoMN\object_detection_demo\object_detection_demo\data\images\rect\5000170.jpg</path>
  <source>
    <database>Unknown</database>
  </source>
  <size>
    <width>800</width>
    <height>600</height>
    <depth>3</depth>
  </size>
  <segmented>0</segmented>
  <object>
    <name>ManaoArotava</name>
    <pose>Unspecified</pose>
    <truncated>0</truncated>
    <difficult>0</difficult>
    <bndbox>
      <xmin>228</xmin>
      <ymin>175</ymin>
      <xmax>331</xmax>
      <ymax>307</ymax>
    </bndbox>
  </object>
  <object>
    <name>ManaoArotava</name>
    <pose>Unspecified</pose>
    <truncated>0</truncated>
    <difficult>0</difficult>
    <bndbox>
      <xmin>18</xmin>
      <ymin>157</ymin>
      <xmax>91</xmax>
      <ymax>226</ymax>
    </bndbox>
  </object>
  <object>
    <name>ManaoArotava</name>
    <pose>Unspecified</pose>
    <truncated>0</truncated>
    <difficult>0</difficult>
    <bndbox>
      <xmin>411</xmin>
      <ymin>171</ymin>
      <xmax>476</xmax>
      <ymax>244</ymax>
    </bndbox>
  </object>
</annotation>
